pyavif-0.0.1.dist-info/RECORD
pyavif-0.0.1.dist-info/WHEEL
pyavif-0.0.1.dist-info/METADATA
pyavif-0.0.1.dist-info/licenses/LICENSE
pyavif/__init__.py
pyavif/pyavif_ext.cpython-39-darwin.so
