Metadata-Version: 2.1
Name: pyavif
Version: 0.0.1
Summary: AVIF bindings for Python with NumPy support
Author-Email: Andrey Volodin <andrey@gracia.ai>
Classifier: License :: OSI Approved :: BSD License
Project-URL: Homepage, https://github.com/gracia-labs/pyavif
Requires-Python: >=3.9
Requires-Dist: numpy>=1.20.0
Provides-Extra: test
Requires-Dist: pytest>=6.0; extra == "test"
Requires-Dist: pytest-cov>=2.10; extra == "test"
Provides-Extra: dev
Requires-Dist: pytest>=6.0; extra == "dev"
Requires-Dist: pytest-cov>=2.10; extra == "dev"
Requires-Dist: ipython; extra == "dev"
Requires-Dist: jupyter; extra == "dev"
Requires-Dist: matplotlib; extra == "dev"
